{
    "key": "group_5bcaac3486a28",
    "title": "Theme Settings",
    "location": [
        [
            {
                "param": "options_page",
                "operator": "==",
                "value": "acf-options-theme-settings"
            }
        ]
    ],
    "menu_order": 0,
    "position": "normal",
    "style": "default",
    "label_placement": "top",
    "instruction_placement": "label",
    "hide_on_screen": [
        "the_content"
    ],
    "active": 1,
    "description": "",
    "fields": [
        {
            "key": "field_5bcaac8904073",
            "label": "Resources",
            "name": "",
            "type": "tab",
            "instructions": "",
            "required": 0,
            "conditional_logic": 0,
            "wrapper": {
                "width": "",
                "class": "",
                "id": ""
            },
            "placement": "top",
            "endpoint": 0
        },
        {
            "key": "field_5bcaac34bf387",
            "label": "Call to Actions",
            "name": "resources_ctas",
            "type": "repeater",
            "instructions": "The resource CTA's will be mixed in with the first page of resource tiles in any resource archive.",
            "required": 0,
            "conditional_logic": 0,
            "wrapper": {
                "width": "",
                "class": "",
                "id": ""
            },
            "collapsed": "",
            "min": 0,
            "max": 0,
            "layout": "block",
            "button_label": "Add CTA",
            "sub_fields": [
                {
                    "key": "field_5bcaac3605dcd",
                    "label": "Image",
                    "name": "image",
                    "type": "image",
                    "instructions": "",
                    "required": 1,
                    "conditional_logic": 0,
                    "wrapper": {
                        "width": "",
                        "class": "",
                        "id": ""
                    },
                    "return_format": "array",
                    "preview_size": "thumbnail",
                    "library": "all",
                    "min_width": "",
                    "min_height": "",
                    "min_size": "",
                    "max_width": "",
                    "max_height": "",
                    "max_size": "",
                    "mime_types": ""
                },
                {
                    "key": "field_5bcaac3605e32",
                    "label": "Title",
                    "name": "title",
                    "type": "text",
                    "instructions": "",
                    "required": 0,
                    "conditional_logic": 0,
                    "wrapper": {
                        "width": "",
                        "class": "",
                        "id": ""
                    },
                    "default_value": "",
                    "placeholder": "",
                    "prepend": "",
                    "append": "",
                    "maxlength": ""
                },
                {
                    "key": "field_5bcaac3605e52",
                    "label": "Subtitle",
                    "name": "subtitle",
                    "type": "text",
                    "instructions": "",
                    "required": 0,
                    "conditional_logic": 0,
                    "wrapper": {
                        "width": "",
                        "class": "",
                        "id": ""
                    },
                    "default_value": "",
                    "placeholder": "",
                    "prepend": "",
                    "append": "",
                    "maxlength": ""
                },
                {
                    "key": "field_5bcaac3605e72",
                    "label": "Link",
                    "name": "link",
                    "type": "link",
                    "instructions": "",
                    "required": 0,
                    "conditional_logic": 0,
                    "wrapper": {
                        "width": "",
                        "class": "",
                        "id": ""
                    },
                    "return_format": "array"
                },
                {
                    "key": "field_5bcaac3605e93",
                    "label": "Link Type",
                    "name": "link_type",
                    "type": "radio",
                    "instructions": "",
                    "required": 0,
                    "conditional_logic": 0,
                    "wrapper": {
                        "width": "",
                        "class": "",
                        "id": ""
                    },
                    "choices": {
                        "green": "Green",
                        "blue": "Blue",
                        "white": "White",
                        "link": "Link"
                    },
                    "allow_null": 0,
                    "other_choice": 0,
                    "default_value": "",
                    "layout": "horizontal",
                    "return_format": "value",
                    "save_other_choice": 0
                }
            ]
        },
        {
            "key": "field_5bcac82e9b07f",
            "label": "Blog",
            "name": "",
            "type": "tab",
            "instructions": "",
            "required": 0,
            "conditional_logic": 0,
            "wrapper": {
                "width": "",
                "class": "",
                "id": ""
            },
            "placement": "top",
            "endpoint": 0
        },
        {
            "key": "field_5bcac8359b080",
            "label": "Call to Actions",
            "name": "blog_ctas",
            "type": "repeater",
            "instructions": "The resource CTA's will be mixed in with the first page of resource tiles in any resource archive.",
            "required": 0,
            "conditional_logic": 0,
            "wrapper": {
                "width": "",
                "class": "",
                "id": ""
            },
            "collapsed": "",
            "min": 0,
            "max": 0,
            "layout": "block",
            "button_label": "Add CTA",
            "sub_fields": [
                {
                    "key": "field_5bcac8d29b086",
                    "label": "Image Style",
                    "name": "image_style",
                    "type": "radio",
                    "instructions": "",
                    "required": 1,
                    "conditional_logic": 0,
                    "wrapper": {
                        "width": "",
                        "class": "",
                        "id": ""
                    },
                    "choices": {
                        "background": "Background",
                        "inline": "Inline"
                    },
                    "allow_null": 0,
                    "other_choice": 0,
                    "default_value": "",
                    "layout": "horizontal",
                    "return_format": "value",
                    "save_other_choice": 0
                },
                {
                    "key": "field_5bcac8359b081",
                    "label": "Image",
                    "name": "image",
                    "type": "image",
                    "instructions": "",
                    "required": 1,
                    "conditional_logic": 0,
                    "wrapper": {
                        "width": "",
                        "class": "",
                        "id": ""
                    },
                    "return_format": "array",
                    "preview_size": "thumbnail",
                    "library": "all",
                    "min_width": "",
                    "min_height": "",
                    "min_size": "",
                    "max_width": "",
                    "max_height": "",
                    "max_size": "",
                    "mime_types": ""
                },
                {
                    "key": "field_5bcac97a9b087",
                    "label": "Tag",
                    "name": "tag",
                    "type": "text",
                    "instructions": "",
                    "required": 1,
                    "conditional_logic": 0,
                    "wrapper": {
                        "width": "",
                        "class": "",
                        "id": ""
                    },
                    "default_value": "",
                    "placeholder": "",
                    "prepend": "",
                    "append": "",
                    "maxlength": ""
                },
                {
                    "key": "field_5bcac8359b082",
                    "label": "Title",
                    "name": "title",
                    "type": "text",
                    "instructions": "",
                    "required": 0,
                    "conditional_logic": 0,
                    "wrapper": {
                        "width": "",
                        "class": "",
                        "id": ""
                    },
                    "default_value": "",
                    "placeholder": "",
                    "prepend": "",
                    "append": "",
                    "maxlength": ""
                },
                {
                    "key": "field_5bcac8359b083",
                    "label": "Subtitle",
                    "name": "subtitle",
                    "type": "text",
                    "instructions": "",
                    "required": 0,
                    "conditional_logic": 0,
                    "wrapper": {
                        "width": "",
                        "class": "",
                        "id": ""
                    },
                    "default_value": "",
                    "placeholder": "",
                    "prepend": "",
                    "append": "",
                    "maxlength": ""
                },
                {
                    "key": "field_5bcac8359b084",
                    "label": "Link",
                    "name": "link",
                    "type": "link",
                    "instructions": "",
                    "required": 1,
                    "conditional_logic": 0,
                    "wrapper": {
                        "width": "",
                        "class": "",
                        "id": ""
                    },
                    "return_format": "array"
                },
                {
                    "key": "field_5bcac8359b085",
                    "label": "Link Type",
                    "name": "link_type",
                    "type": "radio",
                    "instructions": "",
                    "required": 0,
                    "conditional_logic": 0,
                    "wrapper": {
                        "width": "",
                        "class": "",
                        "id": ""
                    },
                    "choices": {
                        "green": "Green",
                        "blue": "Blue",
                        "white": "White",
                        "link": "Link"
                    },
                    "allow_null": 0,
                    "other_choice": 0,
                    "default_value": "",
                    "layout": "horizontal",
                    "return_format": "value",
                    "save_other_choice": 0
                },
                {
                    "key": "field_5bcd17edff707",
                    "label": "Feature on blog post sidebar?",
                    "name": "feature_on_post_sidebar",
                    "type": "true_false",
                    "instructions": "",
                    "required": 0,
                    "conditional_logic": 0,
                    "wrapper": {
                        "width": "",
                        "class": "",
                        "id": ""
                    },
                    "message": "",
                    "default_value": 0,
                    "ui": 0,
                    "ui_on_text": "",
                    "ui_off_text": ""
                },
                {
                    "key": "field_5bd208d3218b9",
                    "label": "Feature in blog post archive?",
                    "name": "feature_in_archive",
                    "type": "true_false",
                    "instructions": "",
                    "required": 0,
                    "conditional_logic": 0,
                    "wrapper": {
                        "width": "",
                        "class": "",
                        "id": ""
                    },
                    "message": "",
                    "default_value": 1,
                    "ui": 0,
                    "ui_on_text": "",
                    "ui_off_text": ""
                }
            ]
        }
    ],
    "modified": 1541045678
}